[
  {
    "id": 5945727073,
    "title": "Lego 42182",
    "timestamp": 1741617854,
    "published_time": "10/03/2025 15:44:14",
    "price": 140,
    "brand": "LEGO",
    "url": "https://www.vinted.fr/items/5945727073-lego-42182"
  },
  {
    "id": 5890134103,
    "title": "Se lego technic 42182",
    "timestamp": 1740741768,
    "published_time": "28/02/2025 12:22:48",
    "price": 135,
    "brand": "LEGO",
    "url": "https://www.vinted.fr/items/5890134103-se-lego-technic-42182"
  },
  {
    "id": 5938722595,
    "title": "Lego 42182 - NASA Apollo maanwagen - NIEUW",
    "timestamp": 1741526386,
    "published_time": "09/03/2025 14:19:46",
    "price": 149,
    "brand": "LEGO",
    "url": "https://www.vinted.fr/items/5938722595-lego-42182-nasa-apollo-maanwagen-nieuw"
  },
  {
    "id": 5791544395,
    "title": "Lego Rover lunare NASA Apollo - LRV set 42182",
    "timestamp": 1739123341,
    "published_time": "09/02/2025 18:49:01",
    "price": 145,
    "brand": "LEGO",
    "url": "https://www.vinted.fr/items/5791544395-lego-rover-lunare-nasa-apollo-lrv-set-42182"
  },
  {
    "id": 5850379436,
    "title": "Lego 42182 NASA Apollo Lunar nuovo",
    "timestamp": 1740083645,
    "published_time": "20/02/2025 21:34:05",
    "price": 190,
    "brand": "LEGO",
    "url": "https://www.vinted.fr/items/5850379436-lego-42182-nasa-apollo-lunar-nuovo"
  },
  {
    "id": 5687857482,
    "title": "Lego Technic 42182 - Véhicule d’exploration lunaire NASA Apollo - LRV",
    "timestamp": 1737457519,
    "published_time": "21/01/2025 12:05:19",
    "price": 179.99,
    "brand": "LEGO",
    "url": "https://www.vinted.fr/items/5687857482-lego-technic-42182-vehicule-dexploration-lunaire-nasa-apollo-lrv"
  },
  {
    "id": 5938918138,
    "title": "Lego Technic 42182 Nasa Apollo Lunar",
    "timestamp": 1741527624,
    "published_time": "09/03/2025 14:40:24",
    "price": 144.99,
    "brand": "LEGO",
    "url": "https://www.vinted.fr/items/5938918138-lego-technic-42182-nasa-apollo-lunar"
  },
  {
    "id": 5813179642,
    "title": "Lego 42182 NASA roving véhicule",
    "timestamp": 1739487189,
    "published_time": "13/02/2025 23:53:09",
    "price": 170,
    "brand": "LEGO",
    "url": "https://www.vinted.fr/items/5813179642-lego-42182-nasa-roving-vehicule"
  },
  {
    "id": 5756028350,
    "title": "Lego NASA apollo lunar 42182 neuf",
    "timestamp": 1738557642,
    "published_time": "03/02/2025 05:40:42",
    "price": 156,
    "brand": "LEGO",
    "url": "https://www.vinted.fr/items/5756028350-lego-nasa-apollo-lunar-42182-neuf"
  },
  {
    "id": 5538468840,
    "title": "LEGO Technic 42182 - Novo e Selado",
    "timestamp": 1734453969,
    "published_time": "17/12/2024 17:46:09",
    "price": 150,
    "brand": "LEGO",
    "url": "https://www.vinted.fr/items/5538468840-lego-technic-42182-novo-e-selado"
  },
  {
    "id": 5535758824,
    "title": "Lego 42182 - Technic NASA - Vehículo de Exploración Lunar NASA Apollo",
    "timestamp": 1734381034,
    "published_time": "16/12/2024 21:30:34",
    "price": 154,
    "brand": "LEGO",
    "url": "https://www.vinted.fr/items/5535758824-lego-42182-technic-nasa-vehiculo-de-exploracion-lunar-nasa-apollo"
  },
  {
    "id": 5252356213,
    "title": "LEGO Technic 42182 Rover lunare NASA Apollo - LRV - Nuovo e Sigillato",
    "timestamp": 1729454057,
    "published_time": "20/10/2024 21:54:17",
    "price": 180,
    "brand": "LEGO",
    "url": "https://www.vinted.fr/items/5252356213-lego-technic-42182-rover-lunare-nasa-apollo-lrv-nuovo-e-sigillato"
  },
  {
    "id": 5565646786,
    "title": "LEGO Technic 42182 Veiculo de Exploração Lunar NASA Apollo LRV",
    "timestamp": 1735313682,
    "published_time": "27/12/2024 16:34:42",
    "price": 170,
    "brand": "LEGO",
    "url": "https://www.vinted.fr/items/5565646786-lego-technic-42182-veiculo-de-exploracao-lunar-nasa-apollo-lrv"
  },
  {
    "id": 5627820546,
    "title": "Lote Vehículo de exploración lunar Nasa Apollo",
    "timestamp": 1736456480,
    "published_time": "09/01/2025 22:01:20",
    "price": 220,
    "brand": "LEGO",
    "url": "https://www.vinted.fr/items/5627820546-lote-vehiculo-de-exploracion-lunar-nasa-apollo"
  },
  {
    "id": 5724178625,
    "title": "LEGO veículo lunar NASA Apollo 42182",
    "timestamp": 1738027739,
    "published_time": "28/01/2025 02:28:59",
    "price": 169,
    "brand": "LEGO",
    "url": "https://www.vinted.fr/items/5724178625-lego-veiculo-lunar-nasa-apollo-42182"
  },
  {
    "id": 5809937979,
    "title": "Lego Vehículo de Exploración Lunar NASA Apollo",
    "timestamp": 1739447519,
    "published_time": "13/02/2025 12:51:59",
    "price": 165,
    "brand": "LEGO",
    "url": "https://www.vinted.fr/items/5809937979-lego-vehiculo-de-exploracion-lunar-nasa-apollo"
  }
]