[
  {
    "id": 5862804569,
    "title": "Neuf - Lego 76294",
    "timestamp": 1740307505,
    "price": 274.9,
    "brand": "LEGO",
    "url": "https://www.vinted.fr/items/5862804569-neuf-lego-76294"
  },
  {
    "id": 5572869823,
    "title": "LEGO sh0978 Groot Baby Minifigure from 76286",
    "timestamp": 1735475857,
    "price": 15,
    "brand": "LEGO",
    "url": "https://www.vinted.fr/items/5572869823-lego-sh0978-groot-baby-minifigure-from-76286"
  },
  {
    "id": 5526854264,
    "title": "LEGO sh976 Gamora Minifigure from 76286",
    "timestamp": 1734200477,
    "price": 18,
    "brand": "LEGO",
    "url": "https://www.vinted.fr/items/5526854264-lego-sh976-gamora-minifigure-from-76286"
  },
  {
    "id": 5520973250,
    "title": "LEGO sh975 Star-Lord Minifigure from 76286",
    "timestamp": 1734086866,
    "price": 16,
    "brand": "LEGO",
    "url": "https://www.vinted.fr/items/5520973250-lego-sh975-star-lord-minifigure-from-76286"
  },
  {
    "id": 5572870494,
    "title": "LEGO sh0975 Star-Lord Minifigure from 76286",
    "timestamp": 1735475863,
    "price": 18,
    "brand": "LEGO",
    "url": "https://www.vinted.fr/items/5572870494-lego-sh0975-star-lord-minifigure-from-76286"
  },
  {
    "id": 5536078231,
    "title": "Lego 76286 - Marvel",
    "timestamp": 1734386423,
    "price": 150,
    "brand": "LEGO",
    "url": "https://www.vinted.fr/items/5536078231-lego-76286-marvel"
  },
  {
    "id": 5811761452,
    "title": "Lego Marvel 76286 The Milano spaceship",
    "timestamp": 1739466280,
    "price": 170,
    "brand": "LEGO",
    "url": "https://www.vinted.fr/items/5811761452-lego-marvel-76286-the-milano-spaceship"
  }
]